pysuper/__init__.py
pysuper/_pysuper.abi3.so
pysuper/build_pysuper.py
pysuper-0.2.91.dist-info/METADATA
pysuper-0.2.91.dist-info/RECORD
pysuper-0.2.91.dist-info/WHEEL
pysuper-0.2.91.dist-info/top_level.txt
