Metadata-Version: 2.1
Name: pysuper
Version: 0.2.91
Summary: Search for oligopeptide fragments
Home-page: https://gitlab.com/structural-fragment-search/super
Author: James Collier
Author-email: james@thecolliers.xyz
License: UNKNOWN
Platform: UNKNOWN
Classifier: Programming Language :: Python :: 3
Classifier: Programming Language :: C
Classifier: Development Status :: 3 - Alpha
Classifier: Intended Audience :: Science/Research
Classifier: License :: OSI Approved :: GNU General Public License v2 or later (GPLv2+)
Classifier: Operating System :: OS Independent
Classifier: Topic :: Scientific/Engineering :: Bio-Informatics
Requires-Dist: cffi (>=1.0.0)
